iso4217/__init__.py
iso4217/__init__.pyi
iso4217/data/currencies.json
iso4217/py.typed
python_iso4217-0.0.8.dist-info/METADATA
python_iso4217-0.0.8.dist-info/WHEEL
python_iso4217-0.0.8.dist-info/LICENSE
python_iso4217-0.0.8.dist-info/RECORD
