Metadata-Version: 2.1
Name: python-iso4217
Version: 0.0.8
Summary: Lightweight ISO 4217 currency package
Home-page: https://github.com/GLEF1X/python-iso4217
Author: GLEF1X
Author-email: glebgar567@gmail.com
Maintainer: GLEF1X
Maintainer-email: glebgar567@gmail.com
Requires-Python: >=3.6,<4.0
Classifier: Programming Language :: Python :: 3
Classifier: Programming Language :: Python :: 3.6
Classifier: Programming Language :: Python :: 3.7
Classifier: Programming Language :: Python :: 3.8
Classifier: Programming Language :: Python :: 3.9
Classifier: Programming Language :: Python :: 3.10
Classifier: Programming Language :: Python :: 3.11
Requires-Dist: ijson (>=3.1.4,<4.0.0)
Project-URL: Repository, https://github.com/GLEF1X/python-iso4217
